my_pkg_demo/__init__.py
my_pkg_demo/module.py
my_pkg_demo-0.0.0.dist-info/METADATA
my_pkg_demo-0.0.0.dist-info/WHEEL
my_pkg_demo-0.0.0.dist-info/entry_points.txt
my_pkg_demo-0.0.0.dist-info/top_level.txt
my_pkg_demo-0.0.0.dist-info/RECORD
