Metadata-Version: 2.1
Name: my_pkg_demo
Version: 0.0.0
Requires-Dist: pytest==8.3.3
